latex2sympy/__init__.py
latex2sympy-1.0.3.dist-info/LICENSE.txt
latex2sympy-1.0.3.dist-info/METADATA
latex2sympy-1.0.3.dist-info/WHEEL
latex2sympy-1.0.3.dist-info/top_level.txt
latex2sympy-1.0.3.dist-info/RECORD
