Metadata-Version: 2.1
Name: latex2sympy
Version: 1.0.3
Summary: Convert latex code to sympy code
Home-page: https://gitlab.com/volkerweissmann/latex2sympy
Author: Volker Weißmann
Author-email: volker.weissmann@gmx.de
License: UNKNOWN
Platform: UNKNOWN
Classifier: Programming Language :: Python :: 3
Classifier: License :: OSI Approved :: GNU Affero General Public License v3 or later (AGPLv3+)
Classifier: Operating System :: OS Independent
